cues/__init__.py
cues/__version__.py
cues/canvas.py
cues/checkbox.py
cues/color.py
cues/confirm.py
cues/constants.py
cues/cue.py
cues/cursor.py
cues/form.py
cues/password.py
cues/select.py
cues/survey.py
cues/theme.py
cues/utils.py
cues/listen/__init__.py
cues/listen/ansi.py
cues/listen/unix.py
cues/listen/windows.py
tests/__init__.py
tests/test_canvas.py
tests/test_checkbox.py
tests/test_color.py
tests/test_confirm.py
tests/test_cue.py
tests/test_cursor.py
tests/test_form.py
tests/test_password.py
tests/test_select.py
tests/test_survey.py
tests/test_unix.py
tests/test_utils.py
tests/test_windows.py
cues-0.3.0.dist-info/LICENSE
cues-0.3.0.dist-info/METADATA
cues-0.3.0.dist-info/WHEEL
cues-0.3.0.dist-info/top_level.txt
cues-0.3.0.dist-info/RECORD
