Metadata-Version: 2.1
Name: cues
Version: 0.3.0
Summary: Elegant and sophisticated prompts to inquire and ask questions at the command line.
Home-page: https://github.com/GBS3/cues
Author: Giovanni Salinas
Author-email: gbs3@protonmail.com
License: MIT
Project-URL: Source, https://github.com/GBS3/cues
Keywords: cues,prompts,questions,inquire,enquire,interview,ask
Platform: UNKNOWN
Classifier: Development Status :: 3 - Alpha
Classifier: Programming Language :: Python :: 3.6
Classifier: Programming Language :: Python :: 3.7
Classifier: Programming Language :: Python :: 3.8
Classifier: Programming Language :: Python :: 3.9
Classifier: License :: OSI Approved :: MIT License
Classifier: Operating System :: OS Independent
